src/__init__.py
mcp_video2text-0.1.2.dist-info/METADATA
mcp_video2text-0.1.2.dist-info/WHEEL
mcp_video2text-0.1.2.dist-info/entry_points.txt
mcp_video2text-0.1.2.dist-info/top_level.txt
mcp_video2text-0.1.2.dist-info/RECORD
