Metadata-Version: 2.4
Name: mcp-video2text
Version: 0.1.2
Summary: Convert online video to text, read it quickly
Project-URL: Homepage, https://github.com/yanyaoer/mcp-video2text
Requires-Python: >=3.10
Requires-Dist: mcp>=1.9.0
Requires-Dist: yt-dlp>=2025.4.30
Provides-Extra: mlx
Requires-Dist: mlx-whisper>=0.4.2; extra == "mlx"
Provides-Extra: cpp
Requires-Dist: pywhispercpp>=1.3.0; extra == "cpp"
